mt5linux/__init__.py
mt5linux/__main__.py
mt5linux-0.1.9.dist-info/LICENSE.txt
mt5linux-0.1.9.dist-info/METADATA
mt5linux-0.1.9.dist-info/WHEEL
mt5linux-0.1.9.dist-info/top_level.txt
mt5linux-0.1.9.dist-info/RECORD
