Metadata-Version: 2.1
Name: mt5linux
Version: 0.1.9
Summary: MetaTrader5 for linux users
Home-page: https://github.com/lucas-campagna/mt5linux
Author: Lucas Prett Campagna
License: MIT
Platform: UNKNOWN
